nbreversible/__init__.py
nbreversible/__main__.py
nbreversible/parselib.py
nbreversible/pytransform.py
nbreversible/reactor/__init__.py
nbreversible/reactor/base.py
nbreversible/reactor/fromnotebook.py
nbreversible/reactor/frompython.py
nbreversible-0.0.0.dist-info/DESCRIPTION.rst
nbreversible-0.0.0.dist-info/METADATA
nbreversible-0.0.0.dist-info/RECORD
nbreversible-0.0.0.dist-info/WHEEL
nbreversible-0.0.0.dist-info/entry_points.txt
nbreversible-0.0.0.dist-info/metadata.json
nbreversible-0.0.0.dist-info/top_level.txt
