Metadata-Version: 2.0
Name: nbreversible
Version: 0.0.0
Summary: -
Home-page: https://github.com/podhmo/nbreversible
Author: podhmo
Author-email: ababjam61+github.com@gmail.com
License: UNKNOWN
Keywords: jupyter nbconvert reversible
Platform: UNKNOWN
Classifier: Programming Language :: Python
Classifier: Programming Language :: Python :: Implementation :: CPython
Requires-Dist: nbformat
Requires-Dist: prestring
Provides-Extra: docs
Provides-Extra: testing
